train_pytorch/__init__.py
train_pytorch/trainer.py
train_pytorch-0.0.3.dist-info/LICENSE
train_pytorch-0.0.3.dist-info/METADATA
train_pytorch-0.0.3.dist-info/WHEEL
train_pytorch-0.0.3.dist-info/top_level.txt
train_pytorch-0.0.3.dist-info/RECORD
